otrs/__init__.py
otrs/__main__.py
otrs/ring.py
py_otrs_NickP05-1.0.0.dist-info/METADATA
py_otrs_NickP05-1.0.0.dist-info/WHEEL
py_otrs_NickP05-1.0.0.dist-info/entry_points.txt
py_otrs_NickP05-1.0.0.dist-info/top_level.txt
py_otrs_NickP05-1.0.0.dist-info/RECORD
